{
  "elements": [
    {
      "constraints": {
        "height": {
          "constant": 0.0,
          "percentage": 0.2
        },
        "left": {
          "constant": 0.0,
          "percentage": 0.2
        },
        "right": {
          "constant": 0.0,
          "percentage": 0.2
        },
        "top": {
          "constant": 0.0,
          "percentage": 0.2
        }
      },
      "id": "0",
      "mediaId": "0",
      "customIconId": "3",
      "type": "media"
    },
    {
      "constraints": {
        "bottom": {
          "constant": 0.0,
          "percentage": 0.0
        },
        "left": {
          "constant": 0.0,
          "percentage": 0.0
        },
        "right": {
          "constant": 0.0,
          "percentage": 0.0
        },
        "top": {
          "constant": 0.0,
          "percentage": 0.0
        }
      },
      "id": "1",
      "imageName": "template_widget_1360.png",
      "type": "image"
    },
    {
      "canvasWidth": 375,
      "constraints": {
        "left": {
          "constant": 0.0,
          "percentage": 0.2
        },
        "right": {
          "constant": 0.0,
          "percentage": 0.2
        },
        "top": {
          "constant": 0.0,
          "percentage": 0.2
        }
      },
      "fontName": "570-CAI978",
      "fontSize": 24,
      "id": "2",
      "placeHolder": "Hi",
      "textAlignment": "left",
      "textColor": "FFFFFF",
      "textId": "0",
      "type": "text"
    },
    {
      "constraints": {
        "height": {
          "constant": 0.0,
          "percentage": 0.0
        },
        "right": {
          "constant": 0.0,
          "percentage": 0.0
        },
        "top": {
          "constant": 0.0,
          "percentage": 0.0
        },
        "width": {
          "constant": 0.0,
          "percentage": 0.0
        }
      },
      "contentMode": "aspectFit",
      "id": "3",
      "type": "mediaIcon"
    }
  ],
  "templateId": 1360
}